trace_shrink/__init__.py
trace_shrink/exporter.py
trace_shrink/open_trace.py
trace_shrink/trace.py
trace_shrink/version.py
trace_shrink/abr/__init__.py
trace_shrink/abr/abr_detector.py
trace_shrink/abr/manifest_stream.py
trace_shrink/entries/__init__.py
trace_shrink/entries/bodylogger_entry.py
trace_shrink/entries/har_entry.py
trace_shrink/entries/multifile_entry.py
trace_shrink/entries/proxyman_entry.py
trace_shrink/entries/requests_entry.py
trace_shrink/entries/trace_entry.py
trace_shrink/readers/__init__.py
trace_shrink/readers/bodylogger_reader.py
trace_shrink/readers/har_reader.py
trace_shrink/readers/multifile_reader.py
trace_shrink/readers/proxyman_log_reader.py
trace_shrink/readers/trace_reader.py
trace_shrink/utils/__init__.py
trace_shrink/utils/formats.py
trace_shrink/utils/highlight.py
trace_shrink/utils/http_utils.py
trace_shrink/writers/__init__.py
trace_shrink/writers/har_writer.py
trace_shrink/writers/multifile_writer.py
trace_shrink/writers/proxyman_writer.py
trace_shrink-2.0.0.dist-info/METADATA
trace_shrink-2.0.0.dist-info/WHEEL
trace_shrink-2.0.0.dist-info/RECORD
