Metadata-Version: 2.4
Name: trace-shrink
Version: 2.0.0
Summary: A tool to analyze captures of ABR streams (HAR or Proxyman).
Author-email: Fabre Lambeau <fabre.lambeau@gmail.com>
Requires-Python: >=3.10
Requires-Dist: yarl>=1.9.0
